zbWidgetLib/__init__.py
zbWidgetLib/base.py
zbWidgetLib/func.py
zbWidgetLib/func.pyi
zbWidgetLib/icon.py
zbWidgetLib/page.py
zbWidgetLib/resources_rc.py
zbWidgetLib/base/__init__.py
zbWidgetLib/base/base.py
zbWidgetLib/base/hook.py
zbWidgetLib/base/icon.py
zbWidgetLib/components/__init__.py
zbWidgetLib/components/button.py
zbWidgetLib/components/card.py
zbWidgetLib/components/file_chooser.py
zbWidgetLib/components/flyout.py
zbWidgetLib/components/image.py
zbWidgetLib/components/info_badge.py
zbWidgetLib/components/loading.py
zbWidgetLib/components/page.py
zbWidgetLib/components/progress.py
zbWidgetLib/components/scroll.py
zbWidgetLib/components/splash_screen.py
zbWidgetLib/components/widget.py
zbWidgetLib/components/window.py
zbWidgetLib/icons/FluentAppsList_black.svg
zbWidgetLib/icons/FluentAppsList_white.svg
zbwidgetlib-3.4.2.dist-info/licenses/LICENSE
zbwidgetlib-3.4.2.dist-info/METADATA
zbwidgetlib-3.4.2.dist-info/WHEEL
zbwidgetlib-3.4.2.dist-info/top_level.txt
zbwidgetlib-3.4.2.dist-info/RECORD
