Metadata-Version: 2.4
Name: zbWidgetLib
Version: 3.4.2
Summary: zb组件库
Author-email: Ianzb <93322252@qq.com>
Maintainer-email: Ianzb <93322252@qq.com>
License: GPLv3 License
Project-URL: Repository, https://github.com/Ianzb/zbWidgetLib/
Keywords: zb,Ianzb,widget,lib
Classifier: Programming Language :: Python :: 3
Classifier: Programming Language :: Python :: 3.13
Classifier: Operating System :: OS Independent
Classifier: Operating System :: Microsoft :: Windows
Classifier: Operating System :: MacOS :: MacOS X
Classifier: Operating System :: POSIX :: Linux
Requires-Python: >=3.12
License-File: LICENSE
Requires-Dist: zbToolLib>=2.0.7
Requires-Dist: QtPy>=2.4.3
Requires-Dist: aenum>=3.1.16
Dynamic: license-file
